file_structure_creator/__init__.py
file_structure_creator/creator.py
file_structure_creator-1.1.0.dist-info/LICENSE
file_structure_creator-1.1.0.dist-info/METADATA
file_structure_creator-1.1.0.dist-info/WHEEL
file_structure_creator-1.1.0.dist-info/entry_points.txt
file_structure_creator-1.1.0.dist-info/top_level.txt
file_structure_creator-1.1.0.dist-info/RECORD
