Metadata-Version: 2.2
Name: file_structure_creator
Version: 1.1.0
Summary: 根据文件描述创建目录结构的小工具
Author: 易源
Author-email: zjxfly@126.com
Classifier: Programming Language :: Python :: 3
Classifier: License :: OSI Approved :: MIT License
Classifier: Operating System :: OS Independent
Requires-Python: >=3.6
License-File: LICENSE
Dynamic: author
Dynamic: author-email
Dynamic: classifier
Dynamic: requires-python
Dynamic: summary
